functions_framework-3.9.0-py3.12-nspkg.pth
functions_framework/__init__.py
functions_framework/__main__.py
functions_framework/_cli.py
functions_framework/_function_registry.py
functions_framework/_typed_event.py
functions_framework/background_event.py
functions_framework/event_conversion.py
functions_framework/exceptions.py
functions_framework/execution_id.py
functions_framework/py.typed
functions_framework/request_timeout.py
functions_framework/_http/__init__.py
functions_framework/_http/asgi.py
functions_framework/_http/flask.py
functions_framework/_http/gunicorn.py
functions_framework/aio/__init__.py
functions_framework-3.9.0.dist-info/licenses/LICENSE
google/cloud/functions/__init__.py
google/cloud/functions/context.py
google/cloud/functions_v1/__init__.py
google/cloud/functions_v1/context.py
google/cloud/functions_v1beta2/__init__.py
google/cloud/functions_v1beta2/context.py
functions_framework-3.9.0.dist-info/METADATA
functions_framework-3.9.0.dist-info/WHEEL
functions_framework-3.9.0.dist-info/entry_points.txt
functions_framework-3.9.0.dist-info/namespace_packages.txt
functions_framework-3.9.0.dist-info/top_level.txt
functions_framework-3.9.0.dist-info/RECORD
